README
setup.py
src/zojax/__init__.py
src/zojax.mr.gae.egg-info/PKG-INFO
src/zojax.mr.gae.egg-info/SOURCES.txt
src/zojax.mr.gae.egg-info/dependency_links.txt
src/zojax.mr.gae.egg-info/entry_points.txt
src/zojax.mr.gae.egg-info/namespace_packages.txt
src/zojax.mr.gae.egg-info/not-zip-safe
src/zojax.mr.gae.egg-info/requires.txt
src/zojax.mr.gae.egg-info/top_level.txt
src/zojax/mr/__init__.py
src/zojax/mr/gae/__init__.py
src/zojax/mr/gae/extension.py