Metadata-Version: 1.0
Name: zojax.mr.gae
Version: 0.3
Summary: Simple GAE-extension for buildout
Home-page: https://github.com/Zojax/zojax.mr.gae
Author: Zojax
Author-email: UNKNOWN
License: GPL
Keywords: gae zojax
Platform: UNKNOWN
Classifier: Programming Language :: Python
Classifier: Framework :: Buildout
Classifier: Topic :: Software Development :: Libraries :: Python Modules
